<?xml version="1.0" encoding="utf-8"?>
<onlineGameShop><produk id="1"><nama>AK47 Air Softgun</nama><brand>Nerf</brand><seller>Paris</seller><harga>1500000</harga><deskripsi>Air Softgun yang memiliki bentuk seperti senapan AK47. Ini merupakan sebuah mainan dan bukan senapan asli.</deskripsi><gambar>uploads/ak47.jpg</gambar></produk><produk id="2"><nama>Logitech G733</nama><brand>Logitech</brand><seller>Okta</seller><harga>1500000</harga><deskripsi>Headset dari Logitech yang terkenal akan kualitas yang diberikan dengan banyak sekali opsi yang dapat dikustomisasi.</deskripsi><gambar>uploads/g733.jpg</gambar></produk><produk id="3"><nama>Logitech G102</nama><brand>Logitech</brand><seller>Yogi</seller><harga>400000</harga><deskripsi>Mouse entry level dari Logitech yang paling ramai digunakan oleh komunitas gamer di dunia.</deskripsi><gambar>uploads/g102.jpg</gambar></produk><produk id="4"><nama>Gaming Chair</nama><brand>Secret Lab</brand><seller>Okta</seller><harga>2000000</harga><deskripsi>Kursi Gaming yang menyajikan kenyamanan ketika bermain game. Kursi dapat diatur posisinya untuk menyesuaikan posisi pengguna sehingga performa bermain tetap optimal.</deskripsi><gambar>uploads/kursigeming.jpg</gambar></produk><produk id="6"><nama>Vandal Araxys Air Softgun</nama><brand>Nerf</brand><seller>Paris</seller><harga>1000000</harga><deskripsi>Air Softgun yang terinspirasi dari game Valorant yaitu senjata Vandal dengan skin Araxys. Ini merupakan mainan air softgun dan bukan senjata asli.</deskripsi><gambar>uploads/vandal.jpg</gambar></produk><produk id="23"><nama>Playstation 5</nama><brand>Playstation</brand><seller>Yogi</seller><harga>5000000</harga><deskripsi>Playstation 5, konsol gaming paling modern yang ada untuk saat ini.</deskripsi><gambar>uploads/PS5.png</gambar></produk><produk id="24"><nama>ROG Zephyrus M16 2021</nama><brand>Asus</brand><seller>Anonymous</seller><harga>18000000</harga><deskripsi>CPU: Intel Core i9-13900H RAM: 32GB DDR5 / 4800Hz GPU: Nvidia GeForce RTX 4070</deskripsi><gambar>uploads/ROGM16.png</gambar></produk></onlineGameShop>
